rpa_suite/__init__.py
rpa_suite/suite.py
rpa_suite/core/__init__.py
rpa_suite/core/artemis.py
rpa_suite/core/asyncrun.py
rpa_suite/core/browser.py
rpa_suite/core/clock.py
rpa_suite/core/date.py
rpa_suite/core/dir.py
rpa_suite/core/email.py
rpa_suite/core/file.py
rpa_suite/core/iris.py
rpa_suite/core/log.py
rpa_suite/core/parallel.py
rpa_suite/core/print.py
rpa_suite/core/regex.py
rpa_suite/core/validate.py
rpa_suite/functions/__create_ss_dir.py
rpa_suite/functions/__init__.py
rpa_suite/functions/_printer.py
rpa_suite/utils/__init__.py
rpa_suite/utils/system.py
rpa_suite-1.6.5.dist-info/licenses/LICENSE
rpa_suite-1.6.5.dist-info/METADATA
rpa_suite-1.6.5.dist-info/WHEEL
rpa_suite-1.6.5.dist-info/top_level.txt
rpa_suite-1.6.5.dist-info/RECORD
