Metadata-Version: 2.4
Name: rpa_suite
Version: 1.6.5
Summary: Conjunto de ferramentas essenciais para Automação RPA com Python, que facilitam o dia a dia de desenvolvimento.
Author: Camilo Costa de Carvalho
Author-email: camilo.carvalho@vettracode.com
License: MIT
Project-URL: Código Fonte, https://github.com/CamiloCCarvalho/rpasuite
Project-URL: Documentação, https://github.com/CamiloCCarvalho/rpasuite/wiki
Project-URL: LinkedIn, https://www.linkedin.com/in/camilocostac/
Keywords: basic-tools,email-tools,email-validation,file-tools,simple-functions,rpa-tools,rpa-functions,Tools,Rpa,Automation,RPA,Automação,Python,Ferramentas de RPA,Automação de Processos,Biblioteca Python para RPA,Bot,Robô,Ferramentas de automação,automation-tools,workflow-automation,rpa-framework,python-bots,automation-library,rpa-development,python-automation-tools
Classifier: Development Status :: 3 - Alpha
Classifier: Programming Language :: Python :: 3.11
Classifier: Programming Language :: Python :: 3.12
Classifier: Programming Language :: Python :: 3.13
Classifier: License :: OSI Approved :: MIT License
Classifier: Intended Audience :: Developers
Classifier: Intended Audience :: Education
Classifier: Intended Audience :: Science/Research
Classifier: Operating System :: Microsoft :: Windows
Classifier: Topic :: Scientific/Engineering :: Artificial Intelligence
Classifier: Topic :: Software Development :: Libraries :: Python Modules
License-File: LICENSE
Requires-Dist: setuptools
Requires-Dist: wheel
Requires-Dist: pywin32
Requires-Dist: colorama
Requires-Dist: colorlog
Requires-Dist: email_validator
Requires-Dist: loguru
Requires-Dist: typing
Requires-Dist: pillow
Requires-Dist: pyautogui
Requires-Dist: requests
Requires-Dist: opencv-python
Dynamic: author
Dynamic: author-email
Dynamic: classifier
Dynamic: description
Dynamic: description-content-type
Dynamic: keywords
Dynamic: license
Dynamic: license-file
Dynamic: project-url
Dynamic: requires-dist
Dynamic: summary
